aztfgen/__init__.py
aztfgen/hcl.py
aztfgen-0.1.0.dist-info/DESCRIPTION.rst
aztfgen-0.1.0.dist-info/METADATA
aztfgen-0.1.0.dist-info/RECORD
aztfgen-0.1.0.dist-info/WHEEL
aztfgen-0.1.0.dist-info/entry_points.txt
aztfgen-0.1.0.dist-info/metadata.json
aztfgen-0.1.0.dist-info/top_level.txt
