Metadata-Version: 2.0
Name: aztfgen
Version: 0.1.0
Summary: Generate terraform config from deployed azure resources.
Home-page: http://github.com/glenjamin/azure-terraform-generate
Author: Glen Mailer
Author-email: glen@stainlessed.co.uk
License: MIT
Platform: UNKNOWN
Requires-Python: >=3.5
